example_app/__init__.py
example_app/example.py
example_app_kc_jenkins-0.0.2.dist-info/METADATA
example_app_kc_jenkins-0.0.2.dist-info/WHEEL
example_app_kc_jenkins-0.0.2.dist-info/top_level.txt
example_app_kc_jenkins-0.0.2.dist-info/RECORD
