Metadata-Version: 2.1
Name: example-app-kc-jenkins
Version: 0.0.2
Summary: A small example package
Author: Marta Arcones
Author-email: marta.arcones@gmail.com
Requires-Python: >=3.9
Requires-Dist: coloredlogs
